README.rst
setup.py
src/fc_matplotlib4mesh/__init__.py
src/fc_matplotlib4mesh/demos.py
src/fc_matplotlib4mesh/simplicial.py
src/fc_matplotlib4mesh/sys.py
src/fc_matplotlib4mesh.egg-info/PKG-INFO
src/fc_matplotlib4mesh.egg-info/SOURCES.txt
src/fc_matplotlib4mesh.egg-info/dependency_links.txt
src/fc_matplotlib4mesh.egg-info/requires.txt
src/fc_matplotlib4mesh.egg-info/top_level.txt