Metadata-Version: 1.1
Name: fc-matplotlib4mesh
Version: 0.1.0
Summary: The fc_matplotlib4mesh package displays simplicial meshes or datas on simplicial meshes by using Matplotlib
Home-page: http://www.math.univ-paris13.fr/~cuvelier/software
Author: Francois Cuvelier
Author-email: cuvelier@math.univ-paris13.fr
License: BSD
Platform: Linux
Platform: Mac OS-X
Platform: Windows
Classifier: Topic :: Scientific/Engineering
